[
	{
		"name": "register-with-home-basic",
		"fileGroups": [
			{
				"srcFolder": "how-to/customize-workspace/public/common",
				"destFolder": "how-to/register-with-home-basic/public/common",
				"files": [
					"images/icon-blue.png",
					"snapshots/developer.snapshot.fin.json",
					"style/app.css",
					"style/style-changed-preload.js",
					"views/platform/of-info.view.fin.json",
					"views/platform/of-info/**/*",
					"dos.json",
					"favicon.ico"
				]
			},
			{
				"srcFolder": "how-to/customize-workspace/scripts",
				"destFolder": "how-to/register-with-home-basic/scripts",
				"files": ["dos.mjs", "kill.mjs", "launch.mjs"]
			},
			{
				"srcFolder": "how-to/customize-workspace/client/types",
				"destFolder": "how-to/register-with-home-basic/client/types",
				"files": ["fin.d.ts"]
			}
		]
	}
]
